invenio_theme_tugraz/__init__.py
invenio_theme_tugraz/config.py
invenio_theme_tugraz/ext.py
invenio_theme_tugraz/search.py
invenio_theme_tugraz/views.py
invenio_theme_tugraz/webpack.py
invenio_theme_tugraz/assets/semantic-ui/js/invenio_theme_tugraz/theme.js
invenio_theme_tugraz/assets/semantic-ui/js/invenio_theme_tugraz/unlock.js
invenio_theme_tugraz/assets/semantic-ui/less/invenio_theme_tugraz/accounts.less
invenio_theme_tugraz/assets/semantic-ui/less/invenio_theme_tugraz/communities.less
invenio_theme_tugraz/assets/semantic-ui/less/invenio_theme_tugraz/deposit.less
invenio_theme_tugraz/assets/semantic-ui/less/invenio_theme_tugraz/footer.less
invenio_theme_tugraz/assets/semantic-ui/less/invenio_theme_tugraz/frontpage.less
invenio_theme_tugraz/assets/semantic-ui/less/invenio_theme_tugraz/header.less
invenio_theme_tugraz/assets/semantic-ui/less/invenio_theme_tugraz/login.less
invenio_theme_tugraz/assets/semantic-ui/less/invenio_theme_tugraz/macros.less
invenio_theme_tugraz/assets/semantic-ui/less/invenio_theme_tugraz/overrides.less
invenio_theme_tugraz/assets/semantic-ui/less/invenio_theme_tugraz/record.less
invenio_theme_tugraz/assets/semantic-ui/less/invenio_theme_tugraz/search.less
invenio_theme_tugraz/assets/semantic-ui/less/invenio_theme_tugraz/theme.less
invenio_theme_tugraz/assets/semantic-ui/less/invenio_theme_tugraz/variables.less
invenio_theme_tugraz/assets/semantic-ui/less/invenio_theme_tugraz/fonts/SourceSansPro/OFL.txt
invenio_theme_tugraz/assets/semantic-ui/less/invenio_theme_tugraz/fonts/SourceSansPro/SourceSansPro-Italic.ttf
invenio_theme_tugraz/assets/semantic-ui/less/invenio_theme_tugraz/fonts/SourceSansPro/SourceSansPro-Regular.ttf
invenio_theme_tugraz/static/favicon.ico
invenio_theme_tugraz/static/extra/orcid.png
invenio_theme_tugraz/static/images/Fair_Data_Austria_orangerot.png
invenio_theme_tugraz/static/images/Icon_1_v2.svg
invenio_theme_tugraz/static/images/SharedRDM-orange.png
invenio_theme_tugraz/static/images/TU_Austria_Logo.png
invenio_theme_tugraz-4.13.7.dist-info/licenses/AUTHORS.rst
invenio_theme_tugraz-4.13.7.dist-info/licenses/LICENSE
invenio_theme_tugraz-4.13.7.dist-info/METADATA
invenio_theme_tugraz-4.13.7.dist-info/WHEEL
invenio_theme_tugraz-4.13.7.dist-info/entry_points.txt
invenio_theme_tugraz-4.13.7.dist-info/top_level.txt
invenio_theme_tugraz-4.13.7.dist-info/RECORD
