Metadata-Version: 2.4
Name: invenio-theme-tugraz
Version: 4.13.7
Summary: "Invenio module for TUGRAZ theme."
Home-page: https://github.com/tu-graz-library/invenio-theme-tugraz
Author: "Graz University of Technology"
Author-email: mojib.wali@tugraz.at
License: MIT
Keywords: invenio theme invenioRDM TU-Graz
Platform: any
Classifier: Environment :: Web Environment
Classifier: Intended Audience :: Developers
Classifier: License :: OSI Approved :: MIT License
Classifier: Operating System :: OS Independent
Classifier: Programming Language :: Python
Classifier: Topic :: Internet :: WWW/HTTP :: Dynamic Content
Classifier: Topic :: Software Development :: Libraries :: Python Modules
Classifier: Programming Language :: Python :: 3.12
Classifier: Development Status :: 3 - Alpha
Requires-Python: >=3.12
License-File: LICENSE
License-File: AUTHORS.rst
Requires-Dist: invenio-assets>=2.0.0
Requires-Dist: invenio-i18n>=1.3.1
Requires-Dist: invenio_config_tugraz>=0.11.0
Requires-Dist: invenio_records_global_search>=0.0.1
Requires-Dist: invenio_records_marc21>=0.21.0
Provides-Extra: tests
Requires-Dist: invenio-app>=2.0.0; extra == "tests"
Requires-Dist: invenio-previewer>=3.0.0; extra == "tests"
Requires-Dist: invenio-search[opensearch2]>=3.0.0; extra == "tests"
Requires-Dist: pytest-black-ng>=0.4.0; extra == "tests"
Requires-Dist: pytest-invenio>=3.0.0; extra == "tests"
Requires-Dist: Sphinx>=4.5.0; extra == "tests"
Dynamic: license-file
